scrapesome/__init__.py
scrapesome/cli.py
scrapesome/config.py
scrapesome/exceptions.py
scrapesome/logging.py
scrapesome/formatter/__init__.py
scrapesome/formatter/output_formatter.py
scrapesome/scraper/__init__.py
scrapesome/scraper/async_scraper.py
scrapesome/scraper/rendering.py
scrapesome/scraper/sync_scraper.py
scrapesome/utils/__init__.py
scrapesome/utils/file_writer.py
scrapesome-0.1.4.dist-info/licenses/LICENSE
scrapesome-0.1.4.dist-info/METADATA
scrapesome-0.1.4.dist-info/WHEEL
scrapesome-0.1.4.dist-info/entry_points.txt
scrapesome-0.1.4.dist-info/top_level.txt
scrapesome-0.1.4.dist-info/RECORD
