Metadata-Version: 2.4
Name: scrapesome
Version: 0.1.4
Summary: A Powerful Web Scraper with dynamic rendering support.
Home-page: https://github.com/scrapesome/scrapesome
Author: Vishnu Vardhan Reddy
Author-email: Vishnu Vardhan Reddy <gvvr2024@gmail.com>
License: MIT License
Project-URL: Homepage, http://scrapesome.github.io/scrapesome
Project-URL: Documentation, http://scrapesome.github.io/scrapesome/documentation
Project-URL: Repository, https://github.com/scrapesome/scrapesome
Classifier: Programming Language :: Python :: 3
Classifier: Programming Language :: Python :: 3.8
Classifier: Programming Language :: Python :: 3.9
Classifier: Programming Language :: Python :: 3.10
Classifier: Programming Language :: Python :: 3.11
Classifier: License :: OSI Approved :: MIT License
Classifier: Operating System :: OS Independent
Requires-Python: >=3.8
License-File: LICENSE
Requires-Dist: python-dotenv<2.0,>=0.5.0
Requires-Dist: playwright<2.0,>=1.40.0
Requires-Dist: beautifulsoup4<5.0,>=4.5.0
Requires-Dist: httpx<1.0,>=0.20.0
Requires-Dist: requests<3.0,>=2.18.0
Requires-Dist: markdownify<2.0,>=1.0.0
Provides-Extra: cli
Requires-Dist: typer[all]>=0.9; extra == "cli"
Dynamic: author
Dynamic: home-page
Dynamic: license-file
